Metadata-Version: 1.0
Name: financetoolbox
Version: 0.1.0
Summary: Financial Toolbox
Home-page: UNKNOWN
Author: Rodrigo H. Mota
Author-email: contact@rhdzmota.com
License: UNKNOWN
Platform: UNKNOWN
